WuaiPojieLuntanjinghuaJi2019DisanBufen/README.md
WuaiPojieLuntanjinghuaJi2019DisanBufen/__init__.py
WuaiPojieLuntanjinghuaJi2019DisanBufen/__main__.py
WuaiPojieLuntanjinghuaJi2019DisanBufen/file.epub
WuaiPojieLuntanjinghuaJi2019DisanBufen/index.html
WuaiPojieLuntanjinghuaJi2019DisanBufen/css/__init__.py
WuaiPojieLuntanjinghuaJi2019DisanBufen/css/annotations.css
WuaiPojieLuntanjinghuaJi2019DisanBufen/css/main.css
WuaiPojieLuntanjinghuaJi2019DisanBufen/css/normalize.css
WuaiPojieLuntanjinghuaJi2019DisanBufen/css/popup.css
WuaiPojieLuntanjinghuaJi2019DisanBufen/font/__init__.py
WuaiPojieLuntanjinghuaJi2019DisanBufen/font/fontello.eot
WuaiPojieLuntanjinghuaJi2019DisanBufen/font/fontello.svg
WuaiPojieLuntanjinghuaJi2019DisanBufen/font/fontello.ttf
WuaiPojieLuntanjinghuaJi2019DisanBufen/font/fontello.woff
WuaiPojieLuntanjinghuaJi2019DisanBufen/img/__init__.py
WuaiPojieLuntanjinghuaJi2019DisanBufen/img/annotator-glyph-sprite.png
WuaiPojieLuntanjinghuaJi2019DisanBufen/img/annotator-icon-sprite.png
WuaiPojieLuntanjinghuaJi2019DisanBufen/img/apple-touch-icon.png
WuaiPojieLuntanjinghuaJi2019DisanBufen/img/cancelfullscreen.png
WuaiPojieLuntanjinghuaJi2019DisanBufen/img/close.png
WuaiPojieLuntanjinghuaJi2019DisanBufen/img/fullscreen.png
WuaiPojieLuntanjinghuaJi2019DisanBufen/img/loader.gif
WuaiPojieLuntanjinghuaJi2019DisanBufen/img/menu-icon.png
WuaiPojieLuntanjinghuaJi2019DisanBufen/img/save.png
WuaiPojieLuntanjinghuaJi2019DisanBufen/img/saved.png
WuaiPojieLuntanjinghuaJi2019DisanBufen/img/settings-s.png
WuaiPojieLuntanjinghuaJi2019DisanBufen/img/settings.png
WuaiPojieLuntanjinghuaJi2019DisanBufen/img/star.png
WuaiPojieLuntanjinghuaJi2019DisanBufen/js/__init__.py
WuaiPojieLuntanjinghuaJi2019DisanBufen/js/epub.js
WuaiPojieLuntanjinghuaJi2019DisanBufen/js/epub.min.js
WuaiPojieLuntanjinghuaJi2019DisanBufen/js/epub.min.map
WuaiPojieLuntanjinghuaJi2019DisanBufen/js/hooks.min.js
WuaiPojieLuntanjinghuaJi2019DisanBufen/js/hooks.min.map
wuai_pojie_luntanjinghua_ji_2019_disan_bufen-2024.3.5.0.dist-info/METADATA
wuai_pojie_luntanjinghua_ji_2019_disan_bufen-2024.3.5.0.dist-info/WHEEL
wuai_pojie_luntanjinghua_ji_2019_disan_bufen-2024.3.5.0.dist-info/entry_points.txt
wuai_pojie_luntanjinghua_ji_2019_disan_bufen-2024.3.5.0.dist-info/top_level.txt
wuai_pojie_luntanjinghua_ji_2019_disan_bufen-2024.3.5.0.dist-info/RECORD
